sqlalchemy_llm_agent/__init__.py
sqlalchemy_llm_agent/agent.py
sqlalchemy_llm_agent/cli.py
sqlalchemy_llm_agent/config.py
sqlalchemy_llm_agent/errors.py
sqlalchemy_llm_agent/tools.py
sqlalchemy_llm_agent-0.1.3.dist-info/licenses/LICENSE
sqlalchemy_llm_agent-0.1.3.dist-info/METADATA
sqlalchemy_llm_agent-0.1.3.dist-info/WHEEL
sqlalchemy_llm_agent-0.1.3.dist-info/entry_points.txt
sqlalchemy_llm_agent-0.1.3.dist-info/top_level.txt
sqlalchemy_llm_agent-0.1.3.dist-info/RECORD
