Metadata-Version: 2.4
Name: sqlalchemy-llm-agent
Version: 0.1.3
Summary: Sqlalchemy nl2sql agent
Home-page: https://github.com/org/sqlalchemy-llm-agent
License: MIT License
Project-URL: Homepage, https://github.com/laricko/sqlalchemy-llm-agent
Requires-Python: >=3.8
License-File: LICENSE
Requires-Dist: langchain[openai]>=1.0.5
Requires-Dist: sqlalchemy>=2.0.44
Dynamic: home-page
Dynamic: license-file
Dynamic: requires-python
